smile_config/__init__.py
smile_config/api.py
smile_config/build.py
smile_config/collections.py
smile_config/config.py
smile_config/extension.py
smile_config/py.typed
smile_config/utils.py
smile_config-0.12.0.dist-info/WHEEL
smile_config-0.12.0.dist-info/METADATA
smile_config-0.12.0.dist-info/RECORD
