Metadata-Version: 2.1
Name: smile-config
Version: 0.12.0
Summary: Generate command line options from dataclasses.
License: MIT
Author-email: Nasy <nasyxx+git@gmail.com>
Requires-Python: >=3.9
Requires-Dist: tomlkit
Requires-Dist: typing-extensions
Provides-Extra: rich
Requires-Dist: rich-argparse>=1.0.0; extra == "rich"
Project-URL: homepage, https://github.com/nasyxx/smile_config
Project-URL: repository, https://github.com/nasyxx/smile_config
